metenox/__init__.py
metenox/admin.py
metenox/app_settings.py
metenox/apps.py
metenox/auth_hooks.py
metenox/esi.py
metenox/models.py
metenox/moons.py
metenox/tasks.py
metenox/urls.py
metenox/api/fuzzwork.py
metenox/locale/en/LC_MESSAGES/django.mo
metenox/locale/en/LC_MESSAGES/django.po
metenox/locale/uk/LC_MESSAGES/django.mo
metenox/locale/uk/LC_MESSAGES/django.po
metenox/management/commands/metenox_load_eve.py
metenox/management/commands/metenox_tag_moons_in_range.py
metenox/management/commands/metenox_update_all_holdings.py
metenox/management/commands/metenox_update_all_prices.py
metenox/management/commands/metenox_update_moons_from_moonmining.py
metenox/migrations/0001_initial.py
metenox/migrations/0002_metenoxtag_alter_general_options_and_more.py
metenox/migrations/0003_remove_metenox_tag_metenox_tags_metenoxtag_default.py
metenox/migrations/0004_alter_metenox_tags.py
metenox/migrations/0005_metenox_last_updated_alter_metenox_tags_and_more.py
metenox/migrations/0006_holdingcorporation_ping_on_value_in_moongoo_bay_and_more.py
metenox/migrations/0007_moontag_moon_tags.py
metenox/migrations/0008_holdingcorporation_add_tags_on_pings.py
metenox/migrations/0009_alter_evetypeprice_eve_type.py
metenox/migrations/__init__.py
metenox/templates/metenox/add_webhook.html
metenox/templates/metenox/base.html
metenox/templates/metenox/corporations.html
metenox/templates/metenox/metenoxes.html
metenox/templates/metenox/moons.html
metenox/templates/metenox/prices.html
metenox/templates/metenox/modals/base.html
metenox/templates/metenox/modals/content_base.html
metenox/templates/metenox/modals/corporation_breakdown.html
metenox/templates/metenox/modals/corporation_notifications.html
metenox/templates/metenox/modals/generic_modal_page.html
metenox/templates/metenox/modals/loader_body.html
metenox/templates/metenox/modals/metenox_details.html
metenox/templates/metenox/modals/moon_details.html
metenox/templates/metenox/partials/corp_footer.html
aa_metenox-1.6.3.dist-info/licenses/LICENSE
aa_metenox-1.6.3.dist-info/WHEEL
aa_metenox-1.6.3.dist-info/METADATA
aa_metenox-1.6.3.dist-info/RECORD
