Metadata-Version: 2.4
Name: aa-metenox
Version: 1.6.3
Summary: Metenox app config
Author-email: T'rahk Rokym <trahk.rokym@gmail.com>
Requires-Python: >=3.8
Classifier: Environment :: Web Environment
Classifier: Framework :: Django
Classifier: Framework :: Django :: 4.0
Classifier: Framework :: Django :: 4.2
Classifier: Intended Audience :: Developers
Classifier: License :: OSI Approved :: MIT License
Classifier: Operating System :: OS Independent
Classifier: Programming Language :: Python
Classifier: Programming Language :: Python :: 3.8
Classifier: Programming Language :: Python :: 3.9
Classifier: Programming Language :: Python :: 3.10
Classifier: Programming Language :: Python :: 3.11
Classifier: Topic :: Internet :: WWW/HTTP
Classifier: Topic :: Internet :: WWW/HTTP :: Dynamic Content
License-File: LICENSE
Requires-Dist: allianceauth>=4.6.0
Requires-Dist: aa-moonmining>=1.11
Requires-Dist: allianceauth-app-utils>=1.25.0
Requires-Dist: django-datatables-view>=1.20.0
Requires-Dist: dhooks-lite>=1.1.0
Requires-Dist: responses>=0.25
Project-URL: Changelog, https://gitlab.com/r0kym/aa-metenox/-/blob/main/CHANGELOG.md
Project-URL: Homepage, https://gitlab.com/r0kym/aa-metenox
Project-URL: Source, https://gitlab.com/r0kym/aa-metenox
Project-URL: Tracker, https://gitlab.com/r0kym/aa-metenox/-/issues
